synthetic/__init__.py
synthetic/__main__.py
synthetic/__version__.py
synthetic/iterdata.py
synthetic/core/__init__.py
synthetic/core/ground_truth.py
synthetic/core/synthesizer.py
synthetic/image/__init__.py
synthetic/image/parser.py
synthetic/image/poisson_blending.py
synthetic/image/synthesizer.py
synthetic/pdf/__init__.py
synthetic/pdf/parser.py
synthetic/pdf/synthesizer.py
synthetic/pdf/utils.py
lucidtech_synthetic-0.6.1.dist-info/LICENSE.md
lucidtech_synthetic-0.6.1.dist-info/METADATA
lucidtech_synthetic-0.6.1.dist-info/WHEEL
lucidtech_synthetic-0.6.1.dist-info/entry_points.txt
lucidtech_synthetic-0.6.1.dist-info/top_level.txt
lucidtech_synthetic-0.6.1.dist-info/RECORD
