Metadata-Version: 2.1
Name: lucidtech-synthetic
Version: 0.6.1
Summary: PDF anonymizer/synthesizer for Cradl
Home-page: https://github.com/LucidtechAI/synthetic
Author: Lucidtech
Author-email: hello@lucidtech.ai
Maintainer: August Kvernmo
Maintainer-email: august@lucidtech.ai
License: Apache 2.0
Platform: Posix; MacOS X; Windows
Classifier: Development Status :: 3 - Alpha
Classifier: Intended Audience :: Developers
Classifier: License :: OSI Approved :: Apache Software License
Classifier: Operating System :: OS Independent
Classifier: Programming Language :: Python :: 3.8
Classifier: Programming Language :: Python :: 3.9
Classifier: Programming Language :: Python :: 3.10
Classifier: Programming Language :: Python :: 3.11
Classifier: Topic :: Internet
License-File: LICENSE.md
Requires-Dist: Babel >=2.10.1
Requires-Dist: Pillow >=9.2.0
Requires-Dist: argcomplete >=2.0.0
Requires-Dist: dateparser >=1.1.1
Requires-Dist: filetype >=1.0.13
Requires-Dist: jsonpath-ng >=1.5.3
Requires-Dist: numpy >=1.21.6
Requires-Dist: pdfminer.six >=20220319
Requires-Dist: pikepdf >=7.2.0
Requires-Dist: pyamg >=4.2.3
Requires-Dist: scikit-image >=0.19.3
Requires-Dist: scikit-learn >=1.0.2
Requires-Dist: scipy >=1.7.3
